workfloz/__init__.py
workfloz/cluster.py
workfloz/component.py
workfloz/entity.py
workfloz/exceptions.py
workfloz/parameter.py
workfloz-0.1.0.dist-info/LICENSE
workfloz-0.1.0.dist-info/WHEEL
workfloz-0.1.0.dist-info/METADATA
workfloz-0.1.0.dist-info/RECORD
