Metadata-Version: 2.1
Name: workfloz
Version: 0.1.0
Summary: A simple library for building complex workflows.
Keywords: workflows,pipelines
Author-email: Maël Jamet <maeljamet@hotmail.com>
Requires-Python: >=3.10
Classifier: Development Status :: 1 - Planning
Classifier: Intended Audience :: Developers
Classifier: License :: OSI Approved :: GNU Affero General Public License v3 or later (AGPLv3+)
Classifier: Operating System :: OS Independent
Classifier: Programming Language :: Python
Classifier: Programming Language :: Python :: 3
Project-URL: Source Code, https://github.com/maejam/workfloz
